sqlite_s3_query.py
sqlite_s3_query-0.0.82.dist-info/METADATA
sqlite_s3_query-0.0.82.dist-info/WHEEL
sqlite_s3_query-0.0.82.dist-info/licenses/LICENSE
sqlite_s3_query-0.0.82.dist-info/RECORD
