Metadata-Version: 2.3
Name: sqlite-s3-query
Version: 0.0.82
Summary: Python context manager to query a SQLite file stored on S3
Project-URL: Home-page, https://github.com/michalc/sqlite-s3-query
Author-email: Michal Charemza <michal@charemza.name>
Classifier: License :: OSI Approved :: MIT License
Classifier: Operating System :: OS Independent
Classifier: Programming Language :: Python :: 3
Requires-Python: >=3.6.7
Requires-Dist: httpx>=0.18.2
Provides-Extra: ci-earliest
Requires-Dist: httpx==0.18.2; extra == 'ci-earliest'
Provides-Extra: ci-latest
Requires-Dist: httpx==0.24.1; extra == 'ci-latest'
Provides-Extra: dev
Requires-Dist: coverage; extra == 'dev'
